{
  "clustering_final": 0.001242,
  "dt": 0.5,
  "clustering_initial": 0.001242,
  "N": 493,
  "kappa_initial": -0.029936,
  "iterations": 50,
  "alpha": 0.5,
  "converged": false,
  "eta": 0.009096205001509016,
  "E": 522,
  "trajectory": [
    {
      "w_gini": 0.0,
      "elapsed_s": 0.0,
      "kappa_min": -0.809091,
      "kappa_range": 0.975758,
      "w_spread": 1.0,
      "w_mean": 1.0,
      "kappa_mean": -0.029936,
      "clustering": 0.001242,
      "w_std": 0.0,
      "kappa_std": 0.259753,
      "kappa_max": 0.166667,
      "t": 0
    },
    {
      "w_gini": 0.055587,
      "elapsed_s": 0.0,
      "kappa_min": -0.651083,
      "kappa_range": 0.778789,
      "w_spread": 1.53,
      "w_mean": 1.0,
      "kappa_mean": -0.036631,
      "clustering": 0.001242,
      "w_std": 0.127961,
      "kappa_std": 0.205282,
      "kappa_max": 0.127706,
      "t": 1
    },
    {
      "w_gini": 0.107135,
      "elapsed_s": 0.0,
      "kappa_min": -0.581229,
      "kappa_range": 0.6858,
      "w_spread": 2.13,
      "w_mean": 1.0,
      "kappa_mean": -0.051753,
      "clustering": 0.001242,
      "w_std": 0.245912,
      "kappa_std": 0.169553,
      "kappa_max": 0.10457,
      "t": 2
    },
    {
      "w_gini": 0.155147,
      "elapsed_s": 0.0,
      "kappa_min": -0.53181,
      "kappa_range": 0.617644,
      "w_spread": 2.87,
      "w_mean": 1.0,
      "kappa_mean": -0.070482,
      "clustering": 0.001242,
      "w_std": 0.353116,
      "kappa_std": 0.144949,
      "kappa_max": 0.085834,
      "t": 3
    },
    {
      "w_gini": 0.199072,
      "elapsed_s": 0.0,
      "kappa_min": -0.495279,
      "kappa_range": 0.562835,
      "w_spread": 3.78,
      "w_mean": 1.0,
      "kappa_mean": -0.090189,
      "clustering": 0.001242,
      "w_std": 0.449638,
      "kappa_std": 0.127938,
      "kappa_max": 0.067556,
      "t": 4
    },
    {
      "w_gini": 0.23876,
      "elapsed_s": 0.0,
      "kappa_min": -0.467321,
      "kappa_range": 0.517183,
      "w_spread": 4.88,
      "w_mean": 1.0,
      "kappa_mean": -0.109364,
      "clustering": 0.001242,
      "w_std": 0.536033,
      "kappa_std": 0.116322,
      "kappa_max": 0.049861,
      "t": 5
    },
    {
      "w_gini": 0.274266,
      "elapsed_s": 0.0,
      "kappa_min": -0.445355,
      "kappa_range": 0.478209,
      "w_spread": 6.17,
      "w_mean": 1.0,
      "kappa_mean": -0.127177,
      "clustering": 0.001242,
      "w_std": 0.613177,
      "kappa_std": 0.108446,
      "kappa_max": 0.032854,
      "t": 6
    },
    {
      "w_gini": 0.305803,
      "elapsed_s": 0.0,
      "kappa_min": -0.427748,
      "kappa_range": 0.444729,
      "w_spread": 7.67,
      "w_mean": 1.0,
      "kappa_mean": -0.143194,
      "clustering": 0.001242,
      "w_std": 0.682107,
      "kappa_std": 0.102987,
      "kappa_max": 0.016981,
      "t": 7
    },
    {
      "w_gini": 0.333668,
      "elapsed_s": 0.0,
      "kappa_min": -0.413335,
      "kappa_range": 0.419537,
      "w_spread": 9.39,
      "w_mean": 1.0,
      "kappa_mean": -0.157287,
      "clustering": 0.001242,
      "w_std": 0.743851,
      "kappa_std": 0.099039,
      "kappa_max": 0.006201,
      "t": 8
    },
    {
      "w_gini": 0.358182,
      "elapsed_s": 0.0,
      "kappa_min": -0.400718,
      "kappa_range": 0.396963,
      "w_spread": 11.34,
      "w_mean": 1.0,
      "kappa_mean": -0.169474,
      "clustering": 0.001242,
      "w_std": 0.799362,
      "kappa_std": 0.095934,
      "kappa_max": -0.003755,
      "t": 9
    },
    {
      "w_gini": 0.379693,
      "elapsed_s": 0.0,
      "kappa_min": -0.378521,
      "kappa_range": 0.365617,
      "w_spread": 13.52,
      "w_mean": 1.0,
      "kappa_mean": -0.179817,
      "clustering": 0.001242,
      "w_std": 0.84931,
      "kappa_std": 0.093125,
      "kappa_max": -0.012904,
      "t": 10
    },
    {
      "w_gini": 0.398445,
      "elapsed_s": 0.0,
      "kappa_min": -0.370769,
      "kappa_range": 0.349487,
      "w_spread": 15.77,
      "w_mean": 1.0,
      "kappa_mean": -0.188382,
      "clustering": 0.001242,
      "w_std": 0.893638,
      "kappa_std": 0.090357,
      "kappa_max": -0.021282,
      "t": 11
    },
    {
      "w_gini": 0.414621,
      "elapsed_s": 0.0,
      "kappa_min": -0.355902,
      "kappa_range": 0.326956,
      "w_spread": 17.43,
      "w_mean": 1.0,
      "kappa_mean": -0.195703,
      "clustering": 0.001242,
      "w_std": 0.931686,
      "kappa_std": 0.087779,
      "kappa_max": -0.028946,
      "t": 12
    },
    {
      "w_gini": 0.428789,
      "elapsed_s": 0.0,
      "kappa_min": -0.352024,
      "kappa_range": 0.316059,
      "w_spread": 19.19,
      "w_mean": 1.0,
      "kappa_mean": -0.201647,
      "clustering": 0.001242,
      "w_std": 0.965947,
      "kappa_std": 0.084999,
      "kappa_max": -0.035965,
      "t": 13
    },
    {
      "w_gini": 0.440897,
      "elapsed_s": 0.0,
      "kappa_min": -0.345727,
      "kappa_range": 0.303311,
      "w_spread": 20.81,
      "w_mean": 1.0,
      "kappa_mean": -0.206721,
      "clustering": 0.001242,
      "w_std": 0.9947,
      "kappa_std": 0.08222,
      "kappa_max": -0.042416,
      "t": 14
    },
    {
      "w_gini": 0.451521,
      "elapsed_s": 0.0,
      "kappa_min": -0.33994,
      "kappa_range": 0.291562,
      "w_spread": 23.5,
      "w_mean": 1.0,
      "kappa_mean": -0.211177,
      "clustering": 0.001242,
      "w_std": 1.020385,
      "kappa_std": 0.079455,
      "kappa_max": -0.048378,
      "t": 15
    },
    {
      "w_gini": 0.461022,
      "elapsed_s": 0.0,
      "kappa_min": -0.33545,
      "kappa_range": 0.281522,
      "w_spread": 26.72,
      "w_mean": 1.0,
      "kappa_mean": -0.215024,
      "clustering": 0.001242,
      "w_std": 1.044179,
      "kappa_std": 0.07665,
      "kappa_max": -0.053929,
      "t": 16
    },
    {
      "w_gini": 0.469525,
      "elapsed_s": 0.0,
      "kappa_min": -0.331744,
      "kappa_range": 0.272608,
      "w_spread": 30.27,
      "w_mean": 1.0,
      "kappa_mean": -0.218141,
      "clustering": 0.001242,
      "w_std": 1.065931,
      "kappa_std": 0.0736,
      "kappa_max": -0.059136,
      "t": 17
    },
    {
      "w_gini": 0.476903,
      "elapsed_s": 0.0,
      "kappa_min": -0.325659,
      "kappa_range": 0.261608,
      "w_spread": 33.41,
      "w_mean": 1.0,
      "kappa_mean": -0.22058,
      "clustering": 0.001242,
      "w_std": 1.084061,
      "kappa_std": 0.07035,
      "kappa_max": -0.064052,
      "t": 18
    },
    {
      "w_gini": 0.483254,
      "elapsed_s": 0.0,
      "kappa_min": -0.317203,
      "kappa_range": 0.248492,
      "w_spread": 36.8,
      "w_mean": 1.0,
      "kappa_mean": -0.222579,
      "clustering": 0.001242,
      "w_std": 1.098504,
      "kappa_std": 0.066948,
      "kappa_max": -0.068711,
      "t": 19
    },
    {
      "w_gini": 0.488862,
      "elapsed_s": 0.0,
      "kappa_min": -0.316224,
      "kappa_range": 0.243081,
      "w_spread": 41.0,
      "w_mean": 1.0,
      "kappa_mean": -0.224175,
      "clustering": 0.001242,
      "w_std": 1.110714,
      "kappa_std": 0.063522,
      "kappa_max": -0.073143,
      "t": 20
    },
    {
      "w_gini": 0.493798,
      "elapsed_s": 0.0,
      "kappa_min": -0.310723,
      "kappa_range": 0.23336,
      "w_spread": 45.46,
      "w_mean": 1.0,
      "kappa_mean": -0.225386,
      "clustering": 0.001242,
      "w_std": 1.120681,
      "kappa_std": 0.059984,
      "kappa_max": -0.077363,
      "t": 21
    },
    {
      "w_gini": 0.49817,
      "elapsed_s": 0.0,
      "kappa_min": -0.303503,
      "kappa_range": 0.222124,
      "w_spread": 49.5,
      "w_mean": 1.0,
      "kappa_mean": -0.226597,
      "clustering": 0.001242,
      "w_std": 1.128617,
      "kappa_std": 0.056721,
      "kappa_max": -0.081379,
      "t": 22
    },
    {
      "w_gini": 0.50229,
      "elapsed_s": 0.1,
      "kappa_min": -0.299593,
      "kappa_range": 0.214385,
      "w_spread": 53.43,
      "w_mean": 1.0,
      "kappa_mean": -0.227954,
      "clustering": 0.001242,
      "w_std": 1.136292,
      "kappa_std": 0.053939,
      "kappa_max": -0.085207,
      "t": 23
    },
    {
      "w_gini": 0.506263,
      "elapsed_s": 0.1,
      "kappa_min": -0.295982,
      "kappa_range": 0.207122,
      "w_spread": 57.73,
      "w_mean": 1.0,
      "kappa_mean": -0.229272,
      "clustering": 0.001242,
      "w_std": 1.144376,
      "kappa_std": 0.051495,
      "kappa_max": -0.08886,
      "t": 24
    },
    {
      "w_gini": 0.509992,
      "elapsed_s": 0.1,
      "kappa_min": -0.292654,
      "kappa_range": 0.200315,
      "w_spread": 62.29,
      "w_mean": 1.0,
      "kappa_mean": -0.230535,
      "clustering": 0.001242,
      "w_std": 1.15209,
      "kappa_std": 0.049317,
      "kappa_max": -0.092339,
      "t": 25
    },
    {
      "w_gini": 0.513501,
      "elapsed_s": 0.0,
      "kappa_min": -0.289531,
      "kappa_range": 0.193878,
      "w_spread": 67.11,
      "w_mean": 1.0,
      "kappa_mean": -0.231721,
      "clustering": 0.001242,
      "w_std": 1.15947,
      "kappa_std": 0.047346,
      "kappa_max": -0.095653,
      "t": 26
    },
    {
      "w_gini": 0.516781,
      "elapsed_s": 0.0,
      "kappa_min": -0.286719,
      "kappa_range": 0.187908,
      "w_spread": 72.2,
      "w_mean": 1.0,
      "kappa_mean": -0.232816,
      "clustering": 0.001242,
      "w_std": 1.166374,
      "kappa_std": 0.045547,
      "kappa_max": -0.098811,
      "t": 27
    },
    {
      "w_gini": 0.519839,
      "elapsed_s": 0.1,
      "kappa_min": -0.286184,
      "kappa_range": 0.184359,
      "w_spread": 77.59,
      "w_mean": 1.0,
      "kappa_mean": -0.233841,
      "clustering": 0.001242,
      "w_std": 1.172693,
      "kappa_std": 0.043906,
      "kappa_max": -0.101825,
      "t": 28
    },
    {
      "w_gini": 0.522699,
      "elapsed_s": 0.0,
      "kappa_min": -0.285614,
      "kappa_range": 0.180904,
      "w_spread": 83.26,
      "w_mean": 1.0,
      "kappa_mean": -0.234807,
      "clustering": 0.001242,
      "w_std": 1.17853,
      "kappa_std": 0.042408,
      "kappa_max": -0.10471,
      "t": 29
    },
    {
      "w_gini": 0.5254,
      "elapsed_s": 0.1,
      "kappa_min": -0.285009,
      "kappa_range": 0.177523,
      "w_spread": 89.23,
      "w_mean": 1.0,
      "kappa_mean": -0.23572,
      "clustering": 0.001242,
      "w_std": 1.184038,
      "kappa_std": 0.041038,
      "kappa_max": -0.107486,
      "t": 30
    },
    {
      "w_gini": 0.527945,
      "elapsed_s": 0.0,
      "kappa_min": -0.284367,
      "kappa_range": 0.174197,
      "w_spread": 95.52,
      "w_mean": 1.0,
      "kappa_mean": -0.236583,
      "clustering": 0.001242,
      "w_std": 1.189286,
      "kappa_std": 0.039779,
      "kappa_max": -0.11017,
      "t": 31
    },
    {
      "w_gini": 0.530353,
      "elapsed_s": 0.0,
      "kappa_min": -0.283684,
      "kappa_range": 0.170903,
      "w_spread": 102.14,
      "w_mean": 1.0,
      "kappa_mean": -0.2374,
      "clustering": 0.001242,
      "w_std": 1.194308,
      "kappa_std": 0.038613,
      "kappa_max": -0.112781,
      "t": 32
    },
    {
      "w_gini": 0.532636,
      "elapsed_s": 0.0,
      "kappa_min": -0.282946,
      "kappa_range": 0.167608,
      "w_spread": 109.09,
      "w_mean": 1.0,
      "kappa_mean": -0.238173,
      "clustering": 0.001242,
      "w_std": 1.199122,
      "kappa_std": 0.037522,
      "kappa_max": -0.115338,
      "t": 33
    },
    {
      "w_gini": 0.534797,
      "elapsed_s": 0.0,
      "kappa_min": -0.282348,
      "kappa_range": 0.164487,
      "w_spread": 116.38,
      "w_mean": 1.0,
      "kappa_mean": -0.238901,
      "clustering": 0.001242,
      "w_std": 1.203729,
      "kappa_std": 0.036488,
      "kappa_max": -0.117861,
      "t": 34
    },
    {
      "w_gini": 0.536844,
      "elapsed_s": 0.0,
      "kappa_min": -0.281764,
      "kappa_range": 0.161397,
      "w_spread": 124.02,
      "w_mean": 1.0,
      "kappa_mean": -0.239579,
      "clustering": 0.001242,
      "w_std": 1.208112,
      "kappa_std": 0.035495,
      "kappa_max": -0.120366,
      "t": 35
    },
    {
      "w_gini": 0.538772,
      "elapsed_s": 0.0,
      "kappa_min": -0.281132,
      "kappa_range": 0.158261,
      "w_spread": 132.02,
      "w_mean": 1.0,
      "kappa_mean": -0.240205,
      "clustering": 0.001242,
      "w_std": 1.212238,
      "kappa_std": 0.034534,
      "kappa_max": -0.122871,
      "t": 36
    },
    {
      "w_gini": 0.54059,
      "elapsed_s": 0.0,
      "kappa_min": -0.28041,
      "kappa_range": 0.155018,
      "w_spread": 140.37,
      "w_mean": 1.0,
      "kappa_mean": -0.240784,
      "clustering": 0.001242,
      "w_std": 1.216085,
      "kappa_std": 0.033598,
      "kappa_max": -0.125392,
      "t": 37
    },
    {
      "w_gini": 0.5423,
      "elapsed_s": 0.0,
      "kappa_min": -0.279554,
      "kappa_range": 0.151611,
      "w_spread": 149.08,
      "w_mean": 1.0,
      "kappa_mean": -0.24132,
      "clustering": 0.001242,
      "w_std": 1.21966,
      "kappa_std": 0.032682,
      "kappa_max": -0.127943,
      "t": 38
    },
    {
      "w_gini": 0.543909,
      "elapsed_s": 0.0,
      "kappa_min": -0.278553,
      "kappa_range": 0.148016,
      "w_spread": 158.13,
      "w_mean": 1.0,
      "kappa_mean": -0.241819,
      "clustering": 0.001242,
      "w_std": 1.222989,
      "kappa_std": 0.031785,
      "kappa_max": -0.130537,
      "t": 39
    },
    {
      "w_gini": 0.545423,
      "elapsed_s": 0.0,
      "kappa_min": -0.277429,
      "kappa_range": 0.144243,
      "w_spread": 167.53,
      "w_mean": 1.0,
      "kappa_mean": -0.242283,
      "clustering": 0.001242,
      "w_std": 1.226089,
      "kappa_std": 0.030906,
      "kappa_max": -0.133186,
      "t": 40
    },
    {
      "w_gini": 0.546847,
      "elapsed_s": 0.0,
      "kappa_min": -0.276217,
      "kappa_range": 0.140317,
      "w_spread": 177.26,
      "w_mean": 1.0,
      "kappa_mean": -0.242714,
      "clustering": 0.001242,
      "w_std": 1.228964,
      "kappa_std": 0.030042,
      "kappa_max": -0.1359,
      "t": 41
    },
    {
      "w_gini": 0.548179,
      "elapsed_s": 0.0,
      "kappa_min": -0.274956,
      "kappa_range": 0.136269,
      "w_spread": 187.31,
      "w_mean": 1.0,
      "kappa_mean": -0.243113,
      "clustering": 0.001242,
      "w_std": 1.231607,
      "kappa_std": 0.029191,
      "kappa_max": -0.138687,
      "t": 42
    },
    {
      "w_gini": 0.549418,
      "elapsed_s": 0.0,
      "kappa_min": -0.273683,
      "kappa_range": 0.132132,
      "w_spread": 197.67,
      "w_mean": 1.0,
      "kappa_mean": -0.24348,
      "clustering": 0.001242,
      "w_std": 1.234007,
      "kappa_std": 0.028353,
      "kappa_max": -0.141551,
      "t": 43
    },
    {
      "w_gini": 0.550573,
      "elapsed_s": 0.0,
      "kappa_min": -0.272438,
      "kappa_range": 0.12794,
      "w_spread": 208.3,
      "w_mean": 1.0,
      "kappa_mean": -0.243821,
      "clustering": 0.001242,
      "w_std": 1.236158,
      "kappa_std": 0.027528,
      "kappa_max": -0.144498,
      "t": 44
    },
    {
      "w_gini": 0.551642,
      "elapsed_s": 0.0,
      "kappa_min": -0.27126,
      "kappa_range": 0.123732,
      "w_spread": 219.18,
      "w_mean": 1.0,
      "kappa_mean": -0.244143,
      "clustering": 0.001242,
      "w_std": 1.238069,
      "kappa_std": 0.026719,
      "kappa_max": -0.147529,
      "t": 45
    },
    {
      "w_gini": 0.552632,
      "elapsed_s": 0.0,
      "kappa_min": -0.270188,
      "kappa_range": 0.120276,
      "w_spread": 230.29,
      "w_mean": 1.0,
      "kappa_mean": -0.244455,
      "clustering": 0.001242,
      "w_std": 1.239768,
      "kappa_std": 0.025928,
      "kappa_max": -0.149912,
      "t": 46
    },
    {
      "w_gini": 0.553554,
      "elapsed_s": 0.0,
      "kappa_min": -0.269252,
      "kappa_range": 0.117912,
      "w_spread": 241.59,
      "w_mean": 1.0,
      "kappa_mean": -0.244764,
      "clustering": 0.001242,
      "w_std": 1.241296,
      "kappa_std": 0.025157,
      "kappa_max": -0.151341,
      "t": 47
    },
    {
      "w_gini": 0.554419,
      "elapsed_s": 0.0,
      "kappa_min": -0.268467,
      "kappa_range": 0.115686,
      "w_spread": 253.04,
      "w_mean": 1.0,
      "kappa_mean": -0.245076,
      "clustering": 0.001242,
      "w_std": 1.242697,
      "kappa_std": 0.024407,
      "kappa_max": -0.152781,
      "t": 48
    },
    {
      "w_gini": 0.555229,
      "elapsed_s": 0.0,
      "kappa_min": -0.267831,
      "kappa_range": 0.113593,
      "w_spread": 264.62,
      "w_mean": 1.0,
      "kappa_mean": -0.24539,
      "clustering": 0.001242,
      "w_std": 1.244005,
      "kappa_std": 0.023676,
      "kappa_max": -0.154239,
      "t": 49
    },
    {
      "w_gini": 0.555994,
      "elapsed_s": 0.0,
      "kappa_min": -0.267368,
      "kappa_range": 0.111651,
      "w_spread": 276.29,
      "w_mean": 1.0,
      "kappa_mean": -0.245707,
      "clustering": 0.001242,
      "w_std": 1.245247,
      "kappa_std": 0.022963,
      "kappa_max": -0.155717,
      "t": 50
    }
  ],
  "network_id": "babelnet_ru",
  "kappa_final": -0.245707,
  "mean_k": 2.1176470588235294
}
